README.md
pyproject.toml
setup.py
md_ext/__init__.py
md_ext/img.py
md_ext.egg-info/PKG-INFO
md_ext.egg-info/SOURCES.txt
md_ext.egg-info/dependency_links.txt
md_ext.egg-info/requires.txt
md_ext.egg-info/top_level.txt