Metadata-Version: 2.1
Name: md-ext
Version: 0.0.3
Summary: Markdown extensions
Home-page: https://github.com/omidraha/md_ext
Author: Omid Raha
Author-email: or@omidraha.com
License: UNKNOWN
Download-URL: https://github.com/omidraha/md_ext/archive/refs/tags/0.0.3.tar.gz
Platform: UNKNOWN
Classifier: Programming Language :: Python :: 3
Classifier: License :: OSI Approved :: MIT License
Classifier: Operating System :: OS Independent
